bitcrawler/__init__.py
bitcrawler/crawler.py
bitcrawler/link_utils.py
bitcrawler/parsing.py
bitcrawler/robots.py
bitcrawler/webpage.py
tests/__init__.py
tests/test_crawler.py
tests/test_link_utils.py
tests/test_parsing.py
tests/test_robots.py
tests/test_webpage.py
bitcrawler-0.1.0.dist-info/LICENSE
bitcrawler-0.1.0.dist-info/METADATA
bitcrawler-0.1.0.dist-info/WHEEL
bitcrawler-0.1.0.dist-info/top_level.txt
bitcrawler-0.1.0.dist-info/RECORD
