Metadata-Version: 2.1
Name: bitcrawler
Version: 0.1.0
Summary: Crawling the web made easy.
Home-page: https://github.com/austynherman112994/bitcrawler
Author: Austyn Herman
Author-email: austynherman112994@gmail.com
License: UNKNOWN
Platform: UNKNOWN
Classifier: Programming Language :: Python :: 3
Classifier: License :: OSI Approved :: Apache Software License
Classifier: Operating System :: OS Independent
Requires-Python: >=3.6
Requires-Dist: requests
Requires-Dist: reppy
Requires-Dist: beautifulsoup4
Requires-Dist: validators
